binalyzer/__init__.py
binalyzer/cli.py
binalyzer/extension.py
binalyzer-1.0.6.data/data/CHANGELOG.md
binalyzer-1.0.6.dist-info/AUTHORS
binalyzer-1.0.6.dist-info/LICENSE.rst
binalyzer-1.0.6.dist-info/METADATA
binalyzer-1.0.6.dist-info/WHEEL
binalyzer-1.0.6.dist-info/entry_points.txt
binalyzer-1.0.6.dist-info/top_level.txt
binalyzer-1.0.6.dist-info/RECORD
