Metadata-Version: 2.1
Name: binalyzer
Version: 1.0.6
Summary: Binary Data Analyzer
Home-page: https://binalyzer.denisvasilik.com
Author: Denis Vasilìk
Author-email: contact@denisvasilik.com
Project-URL: Bug Tracker, https://github.com/denisvasilik/binalyzer/issues/
Project-URL: Documentation, https://binalyzer.readthedocs.io/en/latest/
Project-URL: Source Code, https://github.com/denisvasilik/binalyzer/
Classifier: Programming Language :: Python :: 3.6
Classifier: Operating System :: POSIX :: Linux
License-File: LICENSE.rst
License-File: AUTHORS
Requires-Dist: binalyzer-core (==1.0.5)
Requires-Dist: binalyzer-cli (==1.0.0)
Requires-Dist: binalyzer-data-provider (==1.0.0)
Requires-Dist: binalyzer-template-provider (==1.0.2)
Requires-Dist: binalyzer-rest (==1.0.0)
Requires-Dist: binalyzer-wasm (==1.0.0)
